seavad/__init__.py
seavad/config.py
seavad/main.py
seavad/silero.py
seavad/utils.py
seavad/vad_analyzer.py
seavad-0.0.8.dist-info/LICENSE
seavad-0.0.8.dist-info/METADATA
seavad-0.0.8.dist-info/WHEEL
seavad-0.0.8.dist-info/top_level.txt
seavad-0.0.8.dist-info/RECORD
