Metadata-Version: 2.1
Name: seavad
Version: 0.0.8
Summary: SeaVAD: Voice Activity Detection module with silero and state machine.
Author-email: "Seasalt.ai" <info@seasalt.ai>
Classifier: Programming Language :: Python :: 3
Classifier: License :: OSI Approved :: MIT License
Classifier: Operating System :: OS Independent
Requires-Python: >=3.8
License-File: LICENSE
Requires-Dist: pydantic >=1.9
Requires-Dist: onnxruntime >=1.16.3
Requires-Dist: onnxruntime-extensions >=0.11.0
Requires-Dist: importlib-resources >=6.4.5
Requires-Dist: pytest >=8.3.4
Requires-Dist: pyloudnorm >=0.1.1
Provides-Extra: build
Requires-Dist: twine ==4.0.2 ; extra == 'build'
Requires-Dist: build ==1.0.3 ; extra == 'build'
Provides-Extra: dev
Requires-Dist: black ==23.3.0 ; extra == 'dev'
Requires-Dist: isort ==5.12.0 ; extra == 'dev'
Requires-Dist: pyright ==1.1.314 ; extra == 'dev'
Provides-Extra: test
Requires-Dist: pytest ; extra == 'test'
